facebook/__init__.py
facebook/version.py
facebook2-2.2.1.dist-info/DESCRIPTION.rst
facebook2-2.2.1.dist-info/METADATA
facebook2-2.2.1.dist-info/metadata.json
facebook2-2.2.1.dist-info/RECORD
facebook2-2.2.1.dist-info/top_level.txt
facebook2-2.2.1.dist-info/WHEEL
