Metadata-Version: 2.0
Name: facebook2
Version: 2.2.1
Summary: This client library is designed to support the Facebook Graph API and the official Facebook JavaScript SDK, which is the canonical way to implement Facebook authentication.
Home-page: https://github.com/tino/facebook2
Author: Tino de Bruijn
Author-email: UNKNOWN
License: Apache
Platform: UNKNOWN
Classifier: License :: OSI Approved :: Apache Software License
Classifier: Programming Language :: Python :: 2.6
Classifier: Programming Language :: Python :: 2.7
Classifier: Programming Language :: Python :: 3.3
Classifier: Programming Language :: Python :: 3.4
Requires-Dist: requests
